{
    "id": 58002670,
    "name": "Sakupen Egg",
    "subtitle": "Sakupen que?",
    "author": "Sivlol",
    "verifier": "Ninjedu",
    "verificationDate":"2025-28-10",
    "tags": [
        "medium_demon"
    ],
    "verification": "https://youtu.be/M61Vqi6ryj8?si=k3BdmKnrVFL-4rLw",
    "percentToQualify": "72",
    "positionHistory": [
        {
            "date": "14-01-2026",
            "change": null,
            "position": 21,
            "reason": "Added the position history"
        },
        {
            "date": "14-01-2026",
            "change": -1,
            "position": 22,
            "reason": "Added Falling Up (#1)"
        },
        {
            "date": "22-01-2026",
            "change": -1,
            "position": 23,
            "reason": "Raised Celestia from #25 to #22."
        },
        {
            "date": "22-01-2026",
            "change": -1,
            "position": 24,
            "reason": "Raised FPD17 from #24 to #23"
        },
        {
            "date": "09-02-2026",
            "change": -1,
            "position": 25,
            "reason": "Placed Super Mario Wave at #9"
        },
        {
            "date": "09-02-2026",
            "change": -1,
            "position": 26,
            "reason": "Placed Future Funk III at #9"
        },
        {
            "date": "09-02-2026",
            "change": -1,
            "position": 27,
            "reason": "Placed Leyak at #6"
        }
    ],
    "records": []
}